CHANGELOG.txt
LICENCE.txt
MANIFEST.in
README.md
setup.py
byteworker/__init__.py
byteworker.egg-info/PKG-INFO
byteworker.egg-info/SOURCES.txt
byteworker.egg-info/dependency_links.txt
byteworker.egg-info/top_level.txt